setup.cfg
setup.py
Chapman.egg-info/PKG-INFO
Chapman.egg-info/SOURCES.txt
Chapman.egg-info/dependency_links.txt
Chapman.egg-info/entry_points.txt
Chapman.egg-info/not-zip-safe
Chapman.egg-info/top_level.txt
chapman/__init__.py
chapman/actor.py
chapman/canvas.py
chapman/context.py
chapman/decorators.py
chapman/exc.py
chapman/function.py
chapman/meta.py
chapman/model.py
chapman/worker.py
chapman/tests/__init__.py
chapman/tests/test_actor.py