Metadata-Version: 1.0
Name: Chapman
Version: 0.1dev
Summary: Actor-based job queue
Home-page: UNKNOWN
Author: Rick Copeland
Author-email: rick@arborian.com
License: UNKNOWN
Platform: UNKNOWN
